{
  "timestamp": 1781405032,
  "data": {
    "AED": 3.673696,
    "AFN": 64.15,
    "ALL": 82.15,
    "AMD": 369.18,
    "ANG": -1,
    "AOA": 913.116,
    "ARS": 1430.8092,
    "AUD": 1.424703,
    "AWG": 1.79,
    "AZN": 1.7,
    "BAM": 1.692625,
    "BBD": 1.989998,
    "BDT": 123.15,
    "BGN": 1.692625,
    "BHD": 0.377,
    "BIF": 2969.13,
    "BMD": 1,
    "BND": 1.286199,
    "BOB": 6.96,
    "BRL": 5.118795,
    "BSD": 1,
    "BTC": -1,
    "BTN": 95.534904,
    "BWP": 14.204545,
    "BYN": 2.7715,
    "BZD": 2,
    "CAD": 1.399799,
    "CDF": 2266,
    "CHF": 0.797799,
    "CLP": 897.45,
    "CNY": 6.76579,
    "CNH": -1,
    "COP": 3513.54,
    "CRC": 457.97,
    "CUC": -1,
    "CUP": 24,
    "CVE": 95.426127,
    "CZK": 20.941979,
    "DJF": 177.6,
    "DKK": 6.467894,
    "DOP": 59.3057,
    "DZD": 133.0637,
    "EGP": 52.0551,
    "ERN": 15,
    "ETB": 159.6998,
    "EUR": 0.865425,
    "FJD": 2.252252,
    "FKP": 0.747383,
    "GBP": 0.747383,
    "GEL": 2.68,
    "GGP": -1,
    "GHS": 11.15,
    "GIP": 0.747383,
    "GMD": 72.93,
    "GNF": 8721,
    "GTQ": 7.633,
    "GYD": 209.83,
    "HKD": 7.837692,
    "HNL": 26.6302,
    "HRK": 6.520547,
    "HTG": 131.1104,
    "HUF": 307.189693,
    "IDR": 17958,
    "ILS": 2.943497,
    "IMP": -1,
    "INR": 95.534904,
    "IQD": 1310,
    "IRR": 1375255.000001,
    "ISK": 124.7,
    "JEP": -1,
    "JMD": 157.61,
    "JOD": 0.71,
    "JPY": 160.38984,
    "KES": 129.55,
    "KGS": 87.45,
    "KHR": 4027.25,
    "KMF": 425.761365,
    "KPW": 2.2,
    "KRW": 1514.1183,
    "KWD": 0.3073,
    "KYD": 0.833333,
    "KZT": 488.52,
    "LAK": 22121,
    "LBP": 89500,
    "LKR": 336.25,
    "LRD": 181,
    "LSL": 16.360084,
    "LTL": 2.988141,
    "LVL": 0.608224,
    "LYD": 6.36,
    "MAD": 9.249863,
    "MDL": 17.29,
    "MGA": 4194.04,
    "MKD": 53.2832,
    "MMK": 3658,
    "MNT": 3576,
    "MOP": 8.078813,
    "MRU": 39.85,
    "MUR": 48.0381,
    "MVR": 15.5,
    "MWK": 1751,
    "MXN": 17.2067,
    "MYR": 4.064996,
    "MZN": 63.27,
    "NAD": 16.360084,
    "NGN": 1365.5,
    "NIO": 36.6243,
    "NOK": 9.56429,
    "NPR": 152.855847,
    "NZD": 1.721465,
    "OMR": 0.38505,
    "PAB": 1,
    "PEN": 3.3853,
    "PGK": 4.52284,
    "PHP": 60.794,
    "PKR": 278.432,
    "PLN": 3.683796,
    "PYG": 6124.67,
    "QAR": 3.646496,
    "RON": 4.536195,
    "RSD": 101.46,
    "RUB": 72.904427,
    "RWF": 1469.62,
    "SAR": 3.754596,
    "SBD": 8.271299,
    "SCR": 14.4409,
    "SDG": 3857.8506,
    "SEK": 9.480091,
    "SGD": 1.286199,
    "SHP": 0.747383,
    "SLL": 22708.3,
    "SOS": 568,
    "SRD": 37.686,
    "STD": 21160.8,
    "SVC": 8.75,
    "SYP": 6532,
    "SZL": 16.360084,
    "THB": 32.927967,
    "TJS": 9.3181,
    "TMT": 3.491,
    "TND": 2.934,
    "TOP": 2.42483,
    "TRY": 46.282254,
    "TTD": 6.6954,
    "TWD": 31.636,
    "TZS": 2635,
    "UAH": 44.9256,
    "UGX": 3747.95,
    "USD": 1,
    "UYU": 40.353,
    "UZS": 11976.81,
    "VES": 587.4059,
    "VND": 26400,
    "VUV": 123,
    "WST": 2.796812,
    "XAF": 567.681821,
    "XAG": -1,
    "XAU": -1,
    "XCD": 2.68817,
    "XOF": 567.681821,
    "XPF": 103.272715,
    "YER": 1574.7,
    "ZAR": 16.360084,
    "ZMW": 17.48,
    "ZWL": 68560.994089
  }
}