{
  "timestamp": 1780428997,
  "data": {
    "AED": 3.673896,
    "AFN": 63.8,
    "ALL": 82.42,
    "AMD": 369.35,
    "ANG": -1,
    "AOA": 913.0018,
    "ARS": 1421.4672,
    "AUD": 1.401933,
    "AWG": 1.79,
    "AZN": 1.7,
    "BAM": 1.685187,
    "BBD": 1.989998,
    "BDT": 123.25,
    "BGN": 1.685187,
    "BHD": 0.377,
    "BIF": 2967.48,
    "BMD": 1,
    "BND": 1.280699,
    "BOB": 6.96,
    "BRL": 5.047295,
    "BSD": 1,
    "BTC": -1,
    "BTN": 95.072405,
    "BWP": 14.144272,
    "BYN": 2.7698,
    "BZD": 2,
    "CAD": 1.385199,
    "CDF": 2242.8536,
    "CHF": 0.788699,
    "CLP": 893.89,
    "CNY": 6.769341,
    "CNH": -1,
    "COP": 3678.15,
    "CRC": 460.18,
    "CUC": -1,
    "CUP": 24,
    "CVE": 95.006798,
    "CZK": 20.949979,
    "DJF": 177.6,
    "DKK": 6.440194,
    "DOP": 58.8723,
    "DZD": 133.1556,
    "EGP": 52.0743,
    "ERN": 15,
    "ETB": 158.9778,
    "EUR": 0.861622,
    "FJD": 2.24165,
    "FKP": 0.746045,
    "GBP": 0.746045,
    "GEL": 2.689,
    "GGP": -1,
    "GHS": 11.77,
    "GIP": 0.746045,
    "GMD": 72.71,
    "GNF": 8734,
    "GTQ": 7.635,
    "GYD": 209.83,
    "HKD": 7.838392,
    "HNL": 26.6029,
    "HRK": 6.491894,
    "HTG": 130.9494,
    "HUF": 307.089693,
    "IDR": 17905,
    "ILS": 2.834097,
    "IMP": -1,
    "INR": 95.072405,
    "IQD": 1310,
    "IRR": 1350913,
    "ISK": 123.68,
    "JEP": -1,
    "JMD": 156.41,
    "JOD": 0.71,
    "JPY": 159.78984,
    "KES": 129.55,
    "KGS": 87.45,
    "KHR": 4026,
    "KMF": 423.890451,
    "KPW": 2.2,
    "KRW": 1500.1975,
    "KWD": 0.30675,
    "KYD": 0.833333,
    "KZT": 491.65,
    "LAK": 22018,
    "LBP": 89500,
    "LKR": 330.5,
    "LRD": 182,
    "LSL": 16.394584,
    "LTL": 2.97501,
    "LVL": 0.605552,
    "LYD": 6.3378,
    "MAD": 9.162738,
    "MDL": 17.2,
    "MGA": 4190.9,
    "MKD": 52.9746,
    "MMK": 3658,
    "MNT": 3576,
    "MOP": 8.080978,
    "MRU": 39.8523,
    "MUR": 48.06,
    "MVR": 15.5,
    "MWK": 1751,
    "MXN": 17.378,
    "MYR": 3.972496,
    "MZN": 63.27,
    "NAD": 16.394584,
    "NGN": 1366.5,
    "NIO": 36.6243,
    "NOK": 9.309891,
    "NPR": 152.115848,
    "NZD": 1.692332,
    "OMR": 0.38513,
    "PAB": 1,
    "PEN": 3.4097,
    "PGK": 4.512635,
    "PHP": 61.855,
    "PKR": 278.596,
    "PLN": 3.654196,
    "PYG": 6078.01,
    "QAR": 3.646996,
    "RON": 4.528195,
    "RSD": 101.09,
    "RUB": 72.505327,
    "RWF": 1468.82,
    "SAR": 3.753896,
    "SBD": 8.237232,
    "SCR": 14.4336,
    "SDG": 3544.3946,
    "SEK": 9.348891,
    "SGD": 1.280699,
    "SHP": 0.746045,
    "SLL": 22737.4,
    "SOS": 568,
    "SRD": 37.464,
    "STD": 21077,
    "SVC": 8.75,
    "SYP": 6532,
    "SZL": 16.394584,
    "THB": 32.729967,
    "TJS": 9.2439,
    "TMT": 3.491,
    "TND": 2.921,
    "TOP": 2.405002,
    "TRY": 45.930854,
    "TTD": 6.7084,
    "TWD": 31.335,
    "TZS": 2620,
    "UAH": 44.268,
    "UGX": 3768,
    "USD": 1,
    "UYU": 40.319,
    "UZS": 11996.94,
    "VES": 557.9741,
    "VND": 26385,
    "VUV": 121.82,
    "WST": 2.772387,
    "XAF": 565.187268,
    "XAG": -1,
    "XAU": -1,
    "XCD": 2.68817,
    "XOF": 565.187268,
    "XPF": 102.818906,
    "YER": 1574.7,
    "ZAR": 16.394584,
    "ZMW": 18.25,
    "ZWL": 68768.887943
  }
}